[
  null,
  {
    "id": 1,
    "animationId": 0,
    "consumable": true,
    "damage": {
      "critical": false,
      "elementId": 0,
      "formula": "0",
      "type": 0,
      "variance": 20
    },
    "description": "",
    "effects": [],
    "hitType": 0,
    "iconIndex": 0,
    "itypeId": 1,
    "name": "",
    "note": "",
    "occasion": 0,
    "price": 0,
    "repeats": 1,
    "scope": 7,
    "speed": 0,
    "successRate": 100,
    "tpGain": 0
  },
  {
    "id": 2,
    "animationId": 0,
    "consumable": true,
    "damage": {
      "critical": false,
      "elementId": 0,
      "formula": "0",
      "type": 0,
      "variance": 20
    },
    "description": "",
    "effects": [],
    "hitType": 0,
    "iconIndex": 0,
    "itypeId": 1,
    "name": "",
    "note": "",
    "occasion": 0,
    "price": 0,
    "repeats": 1,
    "scope": 7,
    "speed": 0,
    "successRate": 100,
    "tpGain": 0
  },
  {
    "id": 3,
    "animationId": 0,
    "consumable": true,
    "damage": {
      "critical": false,
      "elementId": 0,
      "formula": "0",
      "type": 0,
      "variance": 20
    },
    "description": "",
    "effects": [],
    "hitType": 0,
    "iconIndex": 0,
    "itypeId": 1,
    "name": "",
    "note": "",
    "occasion": 0,
    "price": 0,
    "repeats": 1,
    "scope": 7,
    "speed": 0,
    "successRate": 100,
    "tpGain": 0
  },
  {
    "id": 4,
    "animationId": 0,
    "consumable": true,
    "damage": {
      "critical": false,
      "elementId": 0,
      "formula": "0",
      "type": 0,
      "variance": 20
    },
    "description": "",
    "effects": [],
    "hitType": 0,
    "iconIndex": 0,
    "itypeId": 1,
    "name": "",
    "note": "",
    "occasion": 0,
    "price": 0,
    "repeats": 1,
    "scope": 7,
    "speed": 0,
    "successRate": 100,
    "tpGain": 0
  },
  {
    "id": 5,
    "animationId": 0,
    "consumable": true,
    "damage": {
      "critical": false,
      "elementId": 0,
      "formula": "0",
      "type": 0,
      "variance": 20
    },
    "description": "",
    "effects": [],
    "hitType": 0,
    "iconIndex": 0,
    "itypeId": 1,
    "name": "",
    "note": "",
    "occasion": 0,
    "price": 0,
    "repeats": 1,
    "scope": 7,
    "speed": 0,
    "successRate": 100,
    "tpGain": 0
  },
  {
    "id": 6,
    "animationId": 0,
    "consumable": true,
    "damage": {
      "critical": false,
      "elementId": 0,
      "formula": "0",
      "type": 0,
      "variance": 20
    },
    "description": "",
    "effects": [],
    "hitType": 0,
    "iconIndex": 0,
    "itypeId": 1,
    "name": "",
    "note": "",
    "occasion": 0,
    "price": 0,
    "repeats": 1,
    "scope": 7,
    "speed": 0,
    "successRate": 100,
    "tpGain": 0
  },
  {
    "id": 7,
    "animationId": 0,
    "consumable": true,
    "damage": {
      "critical": false,
      "elementId": 0,
      "formula": "0",
      "type": 0,
      "variance": 20
    },
    "description": "",
    "effects": [],
    "hitType": 0,
    "iconIndex": 0,
    "itypeId": 1,
    "name": "",
    "note": "",
    "occasion": 0,
    "price": 0,
    "repeats": 1,
    "scope": 7,
    "speed": 0,
    "successRate": 100,
    "tpGain": 0
  },
  {
    "id": 8,
    "animationId": 0,
    "consumable": true,
    "damage": {
      "critical": false,
      "elementId": 0,
      "formula": "0",
      "type": 0,
      "variance": 20
    },
    "description": "",
    "effects": [],
    "hitType": 0,
    "iconIndex": 0,
    "itypeId": 1,
    "name": "",
    "note": "",
    "occasion": 0,
    "price": 0,
    "repeats": 1,
    "scope": 7,
    "speed": 0,
    "successRate": 100,
    "tpGain": 0
  },
  {
    "id": 9,
    "animationId": 0,
    "consumable": false,
    "damage": {
      "critical": false,
      "elementId": 0,
      "formula": "0",
      "type": 0,
      "variance": 20
    },
    "description": "",
    "effects": [],
    "hitType": 0,
    "iconIndex": 0,
    "itypeId": 1,
    "name": "Mask",
    "note": "HideItemNumber\n\n<ExtendDesc:A white mask modeled after a fox. It's not expensive, but\nit's well- maintained and slightly warm to the touch. The\nfeelings of the person who gave it might indeed reside in\nthis imitation.>",
    "occasion": 3,
    "price": 0,
    "repeats": 1,
    "scope": 0,
    "speed": 0,
    "successRate": 100,
    "tpGain": 0
  },
  {
    "id": 10,
    "animationId": 0,
    "consumable": false,
    "damage": {
      "critical": false,
      "elementId": 0,
      "formula": "0",
      "type": 0,
      "variance": 20
    },
    "description": "A candle that seems to have withstood the test of time. Its\nshort wick is blackened, and the white wax has faded, but if\nlit, it would likely remember its purpose.",
    "effects": [],
    "hitType": 0,
    "iconIndex": 0,
    "itypeId": 1,
    "name": "Candle",
    "note": "HideItemNumber",
    "occasion": 3,
    "price": 0,
    "repeats": 1,
    "scope": 0,
    "speed": 0,
    "successRate": 100,
    "tpGain": 0
  },
  {
    "id": 11,
    "animationId": 0,
    "consumable": false,
    "damage": {
      "critical": false,
      "elementId": 0,
      "formula": "0",
      "type": 0,
      "variance": 20
    },
    "description": "A matchstick painted red. Once holding many fires, this\nphosphorous sibling might offer some help in dispelling\ndarkness when struck.",
    "effects": [{ "code": 44, "dataId": 27, "value1": 1, "value2": 0 }],
    "hitType": 0,
    "iconIndex": 0,
    "itypeId": 1,
    "name": "Match",
    "note": "HideItemNumber",
    "occasion": 2,
    "price": 0,
    "repeats": 1,
    "scope": 8,
    "speed": 0,
    "successRate": 100,
    "tpGain": 0
  },
  {
    "id": 12,
    "animationId": 0,
    "consumable": false,
    "damage": {
      "critical": false,
      "elementId": 0,
      "formula": "0",
      "type": 0,
      "variance": 20
    },
    "description": "A worn-out wooden bucket. The robustness has been lost from\nthe bucket that has held water many times, and it remains\nforgotten, no longer serving its purpose of quenching\nthirst.",
    "effects": [],
    "hitType": 0,
    "iconIndex": 0,
    "itypeId": 1,
    "name": "Bucket",
    "note": "HideItemNumber",
    "occasion": 3,
    "price": 0,
    "repeats": 1,
    "scope": 0,
    "speed": 0,
    "successRate": 100,
    "tpGain": 0
  },
  {
    "id": 13,
    "animationId": 0,
    "consumable": false,
    "damage": {
      "critical": false,
      "elementId": 0,
      "formula": "0",
      "type": 0,
      "variance": 20
    },
    "description": "",
    "effects": [],
    "hitType": 0,
    "iconIndex": 0,
    "itypeId": 1,
    "name": "Small Plate",
    "note": "HideItemNumber\n\n<ExtendDesc:A small earthenware dish smaller than the palm of a hand. It\nwas a pair of couple dishes with a faint chip on the edge,\nbut one half has been lost for a long time, making a lonely\nsound.>",
    "occasion": 3,
    "price": 0,
    "repeats": 1,
    "scope": 0,
    "speed": 0,
    "successRate": 100,
    "tpGain": 0
  },
  {
    "id": 14,
    "animationId": 0,
    "consumable": false,
    "damage": {
      "critical": false,
      "elementId": 0,
      "formula": "0",
      "type": 0,
      "variance": 20
    },
    "description": "Hand-knitted rope. Although it is old, the skillfully\ntwisted fibers are durable and capable of realizing the wish\nto withstand weight and the hope of tying knots.",
    "effects": [],
    "hitType": 0,
    "iconIndex": 0,
    "itypeId": 1,
    "name": "Rope",
    "note": "HideItemNumber",
    "occasion": 3,
    "price": 0,
    "repeats": 1,
    "scope": 0,
    "speed": 0,
    "successRate": 100,
    "tpGain": 0
  },
  {
    "id": 15,
    "animationId": 0,
    "consumable": false,
    "damage": {
      "critical": false,
      "elementId": 0,
      "formula": "0",
      "type": 0,
      "variance": 20
    },
    "description": "A bucket attached to a rope, a tsurube. The two tools tied\ntogether might remember the old days when they were immersed\nin well water.",
    "effects": [],
    "hitType": 0,
    "iconIndex": 0,
    "itypeId": 1,
    "name": "Well Bucket",
    "note": "HideItemNumber\n\n<ICS レシピ>\n桶: 1\nロープ: 1\n</ICS レシピ>",
    "occasion": 3,
    "price": 0,
    "repeats": 1,
    "scope": 0,
    "speed": 0,
    "successRate": 100,
    "tpGain": 0
  },
  {
    "id": 16,
    "animationId": 0,
    "consumable": false,
    "damage": {
      "critical": false,
      "elementId": 0,
      "formula": "0",
      "type": 0,
      "variance": 20
    },
    "description": "",
    "effects": [],
    "hitType": 0,
    "iconIndex": 0,
    "itypeId": 1,
    "name": "Dish filled with water",
    "note": "HideItemNumber\n\n<ExtendDesc:A terracotta plate filled with water. The edge is already\nchipped, but the clear water may provide some moisture and a\ntrigger to recall the past.>",
    "occasion": 3,
    "price": 0,
    "repeats": 1,
    "scope": 0,
    "speed": 0,
    "successRate": 100,
    "tpGain": 0
  },
  {
    "id": 17,
    "animationId": 0,
    "consumable": false,
    "damage": {
      "critical": false,
      "elementId": 0,
      "formula": "0",
      "type": 0,
      "variance": 20
    },
    "description": "",
    "effects": [],
    "hitType": 0,
    "iconIndex": 0,
    "itypeId": 1,
    "name": "Rusted Key",
    "note": "HideItemNumber\n\n<ExtendDesc:A key covered in red rust. It seems like it would easily\nbreak with just one use, but there may come a time when one\nmust proceed, even if it means sacrificing it.>",
    "occasion": 3,
    "price": 0,
    "repeats": 1,
    "scope": 0,
    "speed": 0,
    "successRate": 100,
    "tpGain": 0
  },
  {
    "id": 18,
    "animationId": 0,
    "consumable": false,
    "damage": {
      "critical": false,
      "elementId": 0,
      "formula": "0",
      "type": 0,
      "variance": 20
    },
    "description": "",
    "effects": [],
    "hitType": 0,
    "iconIndex": 0,
    "itypeId": 1,
    "name": "Hoe",
    "note": "HideItemNumber\n\n<ExtendDesc:An old farming tool. The hoe, worn thin from being gripped,\nwas once used to obtain sustenance. However, its owner fell\nill and it has not been used for a long time.>",
    "occasion": 3,
    "price": 0,
    "repeats": 1,
    "scope": 0,
    "speed": 0,
    "successRate": 100,
    "tpGain": 0
  },
  {
    "id": 19,
    "animationId": 0,
    "consumable": false,
    "damage": {
      "critical": false,
      "elementId": 0,
      "formula": "0",
      "type": 0,
      "variance": 20
    },
    "description": "A beautiful tortoiseshell hair ornament. It was meant to be\na gift for someone, but it has faded a bit because it has\nnever been used and has been sleeping.",
    "effects": [],
    "hitType": 0,
    "iconIndex": 0,
    "itypeId": 1,
    "name": "Beautiful Hairpin",
    "note": "HideItemNumber",
    "occasion": 3,
    "price": 0,
    "repeats": 1,
    "scope": 0,
    "speed": 0,
    "successRate": 100,
    "tpGain": 0
  },
  {
    "id": 20,
    "animationId": 0,
    "consumable": false,
    "damage": {
      "critical": false,
      "elementId": 0,
      "formula": "0",
      "type": 0,
      "variance": 20
    },
    "description": "Iron scissors. A blade made from old iron, the sharpness is\ndull, but it is well known since ancient times that scissors\nhave more than one use.",
    "effects": [],
    "hitType": 0,
    "iconIndex": 0,
    "itypeId": 1,
    "name": "Sturdy Scissors",
    "note": "HideItemNumber",
    "occasion": 3,
    "price": 0,
    "repeats": 1,
    "scope": 0,
    "speed": 0,
    "successRate": 100,
    "tpGain": 0
  },
  {
    "id": 21,
    "animationId": 0,
    "consumable": false,
    "damage": {
      "critical": false,
      "elementId": 0,
      "formula": "0",
      "type": 0,
      "variance": 20
    },
    "description": "Incense in an old, musty sachet. The small amount of\nfragrant wood left in the tattered bag faintly retains a\nnostalgic scent.",
    "effects": [],
    "hitType": 0,
    "iconIndex": 0,
    "itypeId": 1,
    "name": "Ancient Incense",
    "note": "HideItemNumber",
    "occasion": 3,
    "price": 0,
    "repeats": 1,
    "scope": 0,
    "speed": 0,
    "successRate": 100,
    "tpGain": 0
  },
  {
    "id": 22,
    "animationId": 0,
    "consumable": false,
    "damage": {
      "critical": false,
      "elementId": 0,
      "formula": "0",
      "type": 0,
      "variance": 20
    },
    "description": "",
    "effects": [{ "code": 44, "dataId": 28, "value1": 1, "value2": 0 }],
    "hitType": 0,
    "iconIndex": 0,
    "itypeId": 1,
    "name": "Ancient Letter",
    "note": "HideItemNumber\n\n<ExtendDesc:A letter that has been exposed to the wind and rain for a\nlong time, with almost all of its characters faded away. You\ncan feel the clumsy emotions embedded in the short\nsentences.>",
    "occasion": 2,
    "price": 0,
    "repeats": 1,
    "scope": 2,
    "speed": 0,
    "successRate": 100,
    "tpGain": 0
  },
  {
    "id": 23,
    "animationId": 0,
    "consumable": false,
    "damage": {
      "critical": false,
      "elementId": 0,
      "formula": "0",
      "type": 0,
      "variance": 20
    },
    "description": "An old amulet bag. It contains a talisman wishing for safety\nand someone's name, but it is stained with blood, indicating\nthat it failed to protect its owner.",
    "effects": [],
    "hitType": 0,
    "iconIndex": 0,
    "itypeId": 1,
    "name": "Safety Prayer Charm",
    "note": "HideItemNumber",
    "occasion": 3,
    "price": 0,
    "repeats": 1,
    "scope": 0,
    "speed": 0,
    "successRate": 100,
    "tpGain": 0
  },
  {
    "id": 24,
    "animationId": 0,
    "consumable": false,
    "damage": {
      "critical": false,
      "elementId": 0,
      "formula": "0",
      "type": 0,
      "variance": 20
    },
    "description": "",
    "effects": [],
    "hitType": 0,
    "iconIndex": 0,
    "itypeId": 1,
    "name": "Old Flashlight (Without Batteries)",
    "note": "HideItemNumber\n\n<ExtendDesc:A mysterious flashlight imbued with a strange power. It's\nunusable because the batteries are empty. The handle is\ninscribed with the mantra of the Great Sun Buddha; one\nwonders what the owner wanted to illuminate.>",
    "occasion": 3,
    "price": 0,
    "repeats": 1,
    "scope": 0,
    "speed": 0,
    "successRate": 100,
    "tpGain": 0
  },
  {
    "id": 25,
    "animationId": 0,
    "consumable": false,
    "damage": {
      "critical": false,
      "elementId": 0,
      "formula": "0",
      "type": 0,
      "variance": 20
    },
    "description": "A dry cell battery left behind by a ghost who left their\nfeelings behind. For some reason, it's not dirty and feels\nas if it was left behind for someone.",
    "effects": [],
    "hitType": 0,
    "iconIndex": 0,
    "itypeId": 1,
    "name": "Beautiful Battery",
    "note": "HideItemNumber",
    "occasion": 3,
    "price": 0,
    "repeats": 1,
    "scope": 0,
    "speed": 0,
    "successRate": 100,
    "tpGain": 0
  },
  {
    "id": 26,
    "animationId": 0,
    "consumable": false,
    "damage": {
      "critical": false,
      "elementId": 0,
      "formula": "0",
      "type": 0,
      "variance": 20
    },
    "description": "An old flashlight. The handle is inscribed with the mantra\nof Dainichi Nyorai, and it can illuminate things that are\ninvisible to the eye. However, light is easily seen from the\ndarkness.",
    "effects": [],
    "hitType": 0,
    "iconIndex": 0,
    "itypeId": 1,
    "name": "Old Pocket Flashlight",
    "note": "HideItemNumber\n\n<ExtendDesc:An old flashlight. The mantra of Mahavairocana is written on\nthe handle, and it can illuminate things that are invisible\nto the eye. However, light is easily seen from the darkness.>\n\n<ICS レシピ>\n古びた懐中電灯（電池なし）: 1\nきれいな乾電池: 1\n</ICS レシピ>",
    "occasion": 3,
    "price": 0,
    "repeats": 1,
    "scope": 0,
    "speed": 0,
    "successRate": 100,
    "tpGain": 0
  },
  {
    "id": 27,
    "animationId": 0,
    "consumable": false,
    "damage": {
      "critical": false,
      "elementId": 0,
      "formula": "0",
      "type": 0,
      "variance": 20
    },
    "description": "Covered in rust. It would probably break after one use.",
    "effects": [],
    "hitType": 0,
    "iconIndex": 0,
    "itypeId": 1,
    "name": "Rusted Large Key",
    "note": "HideItemNumber",
    "occasion": 3,
    "price": 0,
    "repeats": 1,
    "scope": 0,
    "speed": 0,
    "successRate": 100,
    "tpGain": 0
  },
  {
    "id": 28,
    "animationId": 0,
    "consumable": false,
    "damage": {
      "critical": false,
      "elementId": 0,
      "formula": "0",
      "type": 0,
      "variance": 20
    },
    "description": "",
    "effects": [],
    "hitType": 0,
    "iconIndex": 0,
    "itypeId": 1,
    "name": "Soul-Collecting Talisman",
    "note": "HideItemNumber\n\n<ExtendDesc:A special talisman created by a psychic who has undergone\nlong and arduous training. It converts people's thoughts\ninto power to exorcise demons and grudges. Although it has\nlost its power, it can exert its effect again by gathering\ngood intentions. Will the talisman be able to dispel the\nregrets of its creator?>",
    "occasion": 3,
    "price": 0,
    "repeats": 1,
    "scope": 0,
    "speed": 0,
    "successRate": 100,
    "tpGain": 0
  },
  {
    "id": 29,
    "animationId": 0,
    "consumable": false,
    "damage": {
      "critical": false,
      "elementId": 0,
      "formula": "0",
      "type": 0,
      "variance": 20
    },
    "description": "",
    "effects": [],
    "hitType": 0,
    "iconIndex": 0,
    "itypeId": 1,
    "name": "Remnant Flames of Admiration",
    "note": "\n\n<ExtendDesc:The purified spirit's feelings of gratitude have turned into\na flame. In the cursed house, positive thoughts remain as\nfire, seeking a place to reside. By gathering them on the\ntalisman, it might be possible to burn away the curse of\nrestraint.>",
    "occasion": 3,
    "price": 0,
    "repeats": 1,
    "scope": 0,
    "speed": 0,
    "successRate": 100,
    "tpGain": 0
  },
  {
    "id": 30,
    "animationId": 0,
    "consumable": false,
    "damage": {
      "critical": false,
      "elementId": 0,
      "formula": "0",
      "type": 0,
      "variance": 20
    },
    "description": "A doll's torso clad in a kimono of Japanese style. It is\nfaintly warm and smaller than usual. It seems to be modeled\nafter a girl, but...",
    "effects": [],
    "hitType": 0,
    "iconIndex": 0,
    "itypeId": 1,
    "name": "Doll's Torso",
    "note": "HideItemNumber",
    "occasion": 3,
    "price": 0,
    "repeats": 1,
    "scope": 0,
    "speed": 0,
    "successRate": 100,
    "tpGain": 0
  },
  {
    "id": 31,
    "animationId": 0,
    "consumable": false,
    "damage": {
      "critical": false,
      "elementId": 0,
      "formula": "0",
      "type": 0,
      "variance": 20
    },
    "description": "",
    "effects": [],
    "hitType": 0,
    "iconIndex": 0,
    "itypeId": 1,
    "name": "Rusted Kodachi",
    "note": "HideItemNumber\n\n<ExtendDesc:An old short sword stuck in a large tree. It is filled with\nthe strong prayers of people. Although it is deeply rusted,\nthe power to pierce through the hardened curse remains.>",
    "occasion": 3,
    "price": 0,
    "repeats": 1,
    "scope": 0,
    "speed": 0,
    "successRate": 100,
    "tpGain": 0
  },
  {
    "id": 32,
    "animationId": 0,
    "consumable": false,
    "damage": {
      "critical": false,
      "elementId": 0,
      "formula": "0",
      "type": 0,
      "variance": 20
    },
    "description": "",
    "effects": [],
    "hitType": 0,
    "iconIndex": 0,
    "itypeId": 1,
    "name": "Rusted Iron Key",
    "note": "HideItemNumber\n\n<ExtendDesc:An iron key that was inside the bag. It is terribly old, but\nthere is no problem using it. Slightly curved as if to\nindicate the fate of its owner, it is covered with reddish-\nbrown rust.>",
    "occasion": 3,
    "price": 0,
    "repeats": 1,
    "scope": 0,
    "speed": 0,
    "successRate": 100,
    "tpGain": 0
  },
  {
    "id": 33,
    "animationId": 0,
    "consumable": false,
    "damage": {
      "critical": false,
      "elementId": 0,
      "formula": "0",
      "type": 0,
      "variance": 20
    },
    "description": "",
    "effects": [],
    "hitType": 0,
    "iconIndex": 0,
    "itypeId": 1,
    "name": "Crossing the Suspension Bridge",
    "note": "HideItemNumber\n\n<ExtendDesc:A picture book with a large suspension bridge. On the other\nside of the suspension bridge, a goat is waving its hand,\nand it seems to be about the protagonist sheep gathering\ncourage to meet a friend.>",
    "occasion": 3,
    "price": 0,
    "repeats": 1,
    "scope": 0,
    "speed": 0,
    "successRate": 100,
    "tpGain": 0
  },
  {
    "id": 34,
    "animationId": 0,
    "consumable": false,
    "damage": {
      "critical": false,
      "elementId": 0,
      "formula": "0",
      "type": 0,
      "variance": 20
    },
    "description": "",
    "effects": [],
    "hitType": 0,
    "iconIndex": 0,
    "itypeId": 1,
    "name": "Singing Princess",
    "note": "HideItemNumber\n\n<ExtendDesc:A picture book about a princess who sings in a castle. It\nseems to be about a princess who is always singing, gets\nbanished from the castle, and becomes friends with the\nforest animals through her singing.>",
    "occasion": 3,
    "price": 0,
    "repeats": 1,
    "scope": 0,
    "speed": 0,
    "successRate": 100,
    "tpGain": 0
  },
  {
    "id": 35,
    "animationId": 0,
    "consumable": false,
    "damage": {
      "critical": false,
      "elementId": 0,
      "formula": "0",
      "type": 0,
      "variance": 20
    },
    "description": "",
    "effects": [],
    "hitType": 0,
    "iconIndex": 0,
    "itypeId": 1,
    "name": "King's Tail",
    "note": "HideItemNumber\n\n<ExtendDesc:A picture book depicting a king with his back turned. It\nseems to be about a king with a tail who sets out on a\njourney with his soldiers to remove the tail, but realizes\nthat it is more important to be accepted for having the tail\nthan to lose it.>",
    "occasion": 3,
    "price": 0,
    "repeats": 1,
    "scope": 0,
    "speed": 0,
    "successRate": 100,
    "tpGain": 0
  },
  {
    "id": 36,
    "animationId": 0,
    "consumable": false,
    "damage": {
      "critical": false,
      "elementId": 0,
      "formula": "0",
      "type": 0,
      "variance": 20
    },
    "description": "",
    "effects": [],
    "hitType": 0,
    "iconIndex": 0,
    "itypeId": 1,
    "name": "Prince of Chocolate",
    "note": "HideItemNumber\n\n<ExtendDesc:A picture book depicting a prince stirring a pot. It seems\nto be about a gluttonous prince who hoarded chocolate for\nhimself, but then realizes that eating together with\neveryone is more delicious than eating alone.>",
    "occasion": 3,
    "price": 0,
    "repeats": 1,
    "scope": 0,
    "speed": 0,
    "successRate": 100,
    "tpGain": 0
  },
  {
    "id": 37,
    "animationId": 0,
    "consumable": false,
    "damage": {
      "critical": false,
      "elementId": 0,
      "formula": "0",
      "type": 0,
      "variance": 20
    },
    "description": "",
    "effects": [],
    "hitType": 0,
    "iconIndex": 0,
    "itypeId": 1,
    "name": "Blue Mermaid Princess",
    "note": "HideItemNumber\n\n<ExtendDesc:A picture book about a mermaid girl. The story seems to be\nabout a mermaid daughter who is entrusted to humans, grows\nup beautifully, but her foster parents are deceived by a\nvillain and she is sold to a human trafficker.>",
    "occasion": 3,
    "price": 0,
    "repeats": 1,
    "scope": 0,
    "speed": 0,
    "successRate": 100,
    "tpGain": 0
  },
  {
    "id": 38,
    "animationId": 0,
    "consumable": false,
    "damage": {
      "critical": false,
      "elementId": 0,
      "formula": "0",
      "type": 0,
      "variance": 20
    },
    "description": "",
    "effects": [],
    "hitType": 0,
    "iconIndex": 0,
    "itypeId": 1,
    "name": "Match and Girl",
    "note": "HideItemNumber\n\n<ExtendDesc:A picture book about a girl who lit a fire. In the cold\ntown, it seems to be about a girl trying to sell matches,\nwho sees the figure of her deceased grandmother in the small\nflame.>",
    "occasion": 3,
    "price": 0,
    "repeats": 1,
    "scope": 0,
    "speed": 0,
    "successRate": 100,
    "tpGain": 0
  },
  {
    "id": 39,
    "animationId": 0,
    "consumable": false,
    "damage": {
      "critical": false,
      "elementId": 0,
      "formula": "0",
      "type": 0,
      "variance": 20
    },
    "description": "",
    "effects": [],
    "hitType": 0,
    "iconIndex": 0,
    "itypeId": 1,
    "name": "Bat's Friend",
    "note": "HideItemNumber\n\n<ExtendDesc:A picture book with a crying bat. In a forest where beasts\nand birds quarrel, the bat claimed to be friends with both,\nbut in the end, it seems to be disliked by both sides.>",
    "occasion": 3,
    "price": 0,
    "repeats": 1,
    "scope": 0,
    "speed": 0,
    "successRate": 100,
    "tpGain": 0
  },
  {
    "id": 40,
    "animationId": 0,
    "consumable": false,
    "damage": {
      "critical": false,
      "elementId": 0,
      "formula": "0",
      "type": 0,
      "variance": 20
    },
    "description": "",
    "effects": [],
    "hitType": 0,
    "iconIndex": 0,
    "itypeId": 1,
    "name": "Happy Prince",
    "note": "HideItemNumber\n\n<ExtendDesc:A picture book with an image of a prince's statue and a\nswallow. It seems to be about a swallow that tries hard to\nfulfill the wish of the immobile prince's statue, but in\ndoing so, it ends up losing something important.>",
    "occasion": 3,
    "price": 0,
    "repeats": 1,
    "scope": 0,
    "speed": 0,
    "successRate": 100,
    "tpGain": 0
  },
  {
    "id": 41,
    "animationId": 0,
    "consumable": false,
    "damage": {
      "critical": false,
      "elementId": 0,
      "formula": "0",
      "type": 0,
      "variance": 20
    },
    "description": "",
    "effects": [],
    "hitType": 0,
    "iconIndex": 0,
    "itypeId": 1,
    "name": "Little Rabbit",
    "note": "HideItemNumber\n\n<ExtendDesc:A small rabbit that came out of a hole in the library. It's\nfluffy and warm, but it doesn't seem to be a living\ncreature. The talkative rabbit seems to have been looking\nfor someone who loves books for a long time.>",
    "occasion": 3,
    "price": 0,
    "repeats": 1,
    "scope": 0,
    "speed": 0,
    "successRate": 100,
    "tpGain": 0
  },
  {
    "id": 42,
    "animationId": 0,
    "consumable": false,
    "damage": {
      "critical": false,
      "elementId": 0,
      "formula": "0",
      "type": 0,
      "variance": 20
    },
    "description": "",
    "effects": [],
    "hitType": 0,
    "iconIndex": 0,
    "itypeId": 1,
    "name": "Doll's Right Arm",
    "note": "HideItemNumber\n\n<ExtendDesc:The right arm of the doll. The hand that harbors a faint\nwarmth has its fingers firmly spread open. The extended\nlittle fingers might be hoping for a future where they can\nhold someone's hand.>",
    "occasion": 3,
    "price": 0,
    "repeats": 1,
    "scope": 0,
    "speed": 0,
    "successRate": 100,
    "tpGain": 0
  },
  {
    "id": 43,
    "animationId": 0,
    "consumable": false,
    "damage": {
      "critical": false,
      "elementId": 0,
      "formula": "0",
      "type": 0,
      "variance": 20
    },
    "description": "",
    "effects": [],
    "hitType": 0,
    "iconIndex": 0,
    "itypeId": 1,
    "name": "Doll's Left Arm",
    "note": "HideItemNumber\n\n<ExtendDesc:The doll's left arm. The faintly warm small hand is clenched\nas if clinging to something. This small hand might be\nseeking someone to soothe its loneliness.>",
    "occasion": 3,
    "price": 0,
    "repeats": 1,
    "scope": 0,
    "speed": 0,
    "successRate": 100,
    "tpGain": 0
  },
  {
    "id": 44,
    "animationId": 0,
    "consumable": false,
    "damage": {
      "critical": false,
      "elementId": 0,
      "formula": "0",
      "type": 0,
      "variance": 20
    },
    "description": "",
    "effects": [],
    "hitType": 0,
    "iconIndex": 0,
    "itypeId": 1,
    "name": "Doll's Right Leg",
    "note": "HideItemNumber\n\n<ExtendDesc:Doll's right leg. From the moist heat, one can feel the\nvitality dwelling in the doll. The balance and size of the\nleg clearly indicate that it belongs to a child.>",
    "occasion": 3,
    "price": 0,
    "repeats": 1,
    "scope": 0,
    "speed": 0,
    "successRate": 100,
    "tpGain": 0
  },
  {
    "id": 45,
    "animationId": 0,
    "consumable": false,
    "damage": {
      "critical": false,
      "elementId": 0,
      "formula": "0",
      "type": 0,
      "variance": 20
    },
    "description": "",
    "effects": [],
    "hitType": 0,
    "iconIndex": 0,
    "itypeId": 1,
    "name": "Doll's Left Leg",
    "note": "HideItemNumber\n\n<ExtendDesc:Doll's left leg. The slightly warm leg feels thin and very\ndelicate. It must be modeled after a well-cared-for child\nfrom a good family.>",
    "occasion": 3,
    "price": 0,
    "repeats": 1,
    "scope": 0,
    "speed": 0,
    "successRate": 100,
    "tpGain": 0
  },
  {
    "id": 46,
    "animationId": 0,
    "consumable": false,
    "damage": {
      "critical": false,
      "elementId": 0,
      "formula": "0",
      "type": 0,
      "variance": 20
    },
    "description": "",
    "effects": [],
    "hitType": 0,
    "iconIndex": 0,
    "itypeId": 1,
    "name": "Doll's Head",
    "note": "HideItemNumber\n\n<ExtendDesc:Doll's head. The long, beautiful black hair and the white,\nwell- arranged features are just like Saku. It seems that\nthis doll was indeed made in the image of Saku.>",
    "occasion": 3,
    "price": 0,
    "repeats": 1,
    "scope": 0,
    "speed": 0,
    "successRate": 100,
    "tpGain": 0
  },
  {
    "id": 47,
    "animationId": 0,
    "consumable": false,
    "damage": {
      "critical": false,
      "elementId": 0,
      "formula": "0",
      "type": 0,
      "variance": 20
    },
    "description": "",
    "effects": [],
    "hitType": 0,
    "iconIndex": 0,
    "itypeId": 1,
    "name": "Bath Set",
    "note": "HideItemNumber\n\n<ExtendDesc:Bathing supplies found indoors. A camellia-scented shampoo\nand a white soap were stored unopened. They seem usable as\nthey are well- preserved.>",
    "occasion": 3,
    "price": 0,
    "repeats": 1,
    "scope": 0,
    "speed": 0,
    "successRate": 100,
    "tpGain": 0
  },
  {
    "id": 48,
    "animationId": 0,
    "consumable": false,
    "damage": {
      "critical": false,
      "elementId": 0,
      "formula": "0",
      "type": 0,
      "variance": 20
    },
    "description": "A worn-out dry cell battery. There's only one, but it might\nstill be able to power a small device.",
    "effects": [],
    "hitType": 0,
    "iconIndex": 0,
    "itypeId": 1,
    "name": "Old Battery",
    "note": "HideItemNumber",
    "occasion": 3,
    "price": 0,
    "repeats": 1,
    "scope": 0,
    "speed": 0,
    "successRate": 100,
    "tpGain": 0
  },
  {
    "id": 49,
    "animationId": 0,
    "consumable": false,
    "damage": {
      "critical": false,
      "elementId": 0,
      "formula": "0",
      "type": 0,
      "variance": 20
    },
    "description": "",
    "effects": [],
    "hitType": 0,
    "iconIndex": 0,
    "itypeId": 1,
    "name": "Strawberry Cake",
    "note": "HideItemNumber\n\n<ExtendDesc:Strawberry cake. It is beautifully decorated with whipped\ncream. It seems to be for celebrating someone's birthday,\nbut not a single bite has been taken.>",
    "occasion": 3,
    "price": 0,
    "repeats": 1,
    "scope": 0,
    "speed": 0,
    "successRate": 100,
    "tpGain": 0
  },
  {
    "id": 50,
    "animationId": 0,
    "consumable": false,
    "damage": {
      "critical": false,
      "elementId": 0,
      "formula": "0",
      "type": 0,
      "variance": 20
    },
    "description": "",
    "effects": [],
    "hitType": 0,
    "iconIndex": 0,
    "itypeId": 1,
    "name": "Birthday Candle",
    "note": "HideItemNumber\n\n<ExtendDesc:A candle colored with red and green pigments. Perhaps the\nsmall, unused candle was meant to celebrate someone.>",
    "occasion": 3,
    "price": 0,
    "repeats": 1,
    "scope": 0,
    "speed": 0,
    "successRate": 100,
    "tpGain": 0
  },
  {
    "id": 51,
    "animationId": 0,
    "consumable": false,
    "damage": {
      "critical": false,
      "elementId": 0,
      "formula": "0",
      "type": 0,
      "variance": 20
    },
    "description": "A cake decorated with six candles and strawberries. The\nchild who was supposed to be celebrated never got to see a\nbirthday cake until the end.",
    "effects": [],
    "hitType": 0,
    "iconIndex": 0,
    "itypeId": 1,
    "name": "Birthday Cake",
    "note": "HideItemNumber\n\n<ICS レシピ>\n苺のケーキ: 1\nバースデーキャンドル: 1\n</ICS レシピ>",
    "occasion": 3,
    "price": 0,
    "repeats": 1,
    "scope": 0,
    "speed": 0,
    "successRate": 100,
    "tpGain": 0
  },
  {
    "id": 52,
    "animationId": 0,
    "consumable": false,
    "damage": {
      "critical": false,
      "elementId": 0,
      "formula": "0",
      "type": 0,
      "variance": 20
    },
    "description": "",
    "effects": [],
    "hitType": 0,
    "iconIndex": 0,
    "itypeId": 1,
    "name": "Remote Control",
    "note": "HideItemNumber\n\n<ExtendDesc:A remote control found in a private house. It's dirty, but\nit seems like it could still be used if batteries are put\nin. It's probably for operating the room's air conditioning\nsystem.>",
    "occasion": 3,
    "price": 0,
    "repeats": 1,
    "scope": 0,
    "speed": 0,
    "successRate": 100,
    "tpGain": 0
  },
  {
    "id": 53,
    "animationId": 0,
    "consumable": false,
    "damage": {
      "critical": false,
      "elementId": 0,
      "formula": "0",
      "type": 0,
      "variance": 20
    },
    "description": "A remote control found in a private house. If you insert\nbatteries and turn it on near the air conditioner, you can\nalleviate the scorching heat of the room.",
    "effects": [],
    "hitType": 0,
    "iconIndex": 0,
    "itypeId": 1,
    "name": "Remote Control with Batteries",
    "note": "HideItemNumber\n\n<ICS レシピ>\nリモコン: 1\n古い電池: 1\n</ICS レシピ>",
    "occasion": 3,
    "price": 0,
    "repeats": 1,
    "scope": 0,
    "speed": 0,
    "successRate": 100,
    "tpGain": 0
  },
  {
    "id": 54,
    "animationId": 0,
    "consumable": false,
    "damage": {
      "critical": false,
      "elementId": 0,
      "formula": "0",
      "type": 0,
      "variance": 20
    },
    "description": "A small ignition device found in the garden. The fuel is\nscant, but there is enough left for a few uses.",
    "effects": [],
    "hitType": 0,
    "iconIndex": 0,
    "itypeId": 1,
    "name": "Lighter",
    "note": "HideItemNumber",
    "occasion": 3,
    "price": 0,
    "repeats": 1,
    "scope": 0,
    "speed": 0,
    "successRate": 100,
    "tpGain": 0
  },
  {
    "id": 55,
    "animationId": 0,
    "consumable": false,
    "damage": {
      "critical": false,
      "elementId": 0,
      "formula": "0",
      "type": 0,
      "variance": 20
    },
    "description": "",
    "effects": [],
    "hitType": 0,
    "iconIndex": 0,
    "itypeId": 1,
    "name": "Red Key of Paired Wings",
    "note": "HideItemNumber\n\n<ExtendDesc:A key found in a western-style mansion. It has a grip shaped\nlike a bird with one wing, and a small red gem is inlaid.\nPerhaps the bird with matching wings was able to find its\nother half.>",
    "occasion": 3,
    "price": 0,
    "repeats": 1,
    "scope": 0,
    "speed": 0,
    "successRate": 100,
    "tpGain": 0
  },
  {
    "id": 56,
    "animationId": 0,
    "consumable": false,
    "damage": {
      "critical": false,
      "elementId": 0,
      "formula": "0",
      "type": 0,
      "variance": 20
    },
    "description": "",
    "effects": [],
    "hitType": 0,
    "iconIndex": 0,
    "itypeId": 1,
    "name": "Blue Key of Paired Wings",
    "note": "HideItemNumber\n\n<ExtendDesc:A key found in a western-style mansion. It has a grip shaped\nlike a bird with one wing, and a small blue gem is inlaid.\nPerhaps the bird with matching wings was able to find its\nother half.>",
    "occasion": 3,
    "price": 0,
    "repeats": 1,
    "scope": 0,
    "speed": 0,
    "successRate": 100,
    "tpGain": 0
  },
  {
    "id": 57,
    "animationId": 0,
    "consumable": false,
    "damage": {
      "critical": false,
      "elementId": 0,
      "formula": "0",
      "type": 0,
      "variance": 20
    },
    "description": "",
    "effects": [],
    "hitType": 0,
    "iconIndex": 0,
    "itypeId": 1,
    "name": "Doll's Eye",
    "note": "HideItemNumber\n\n<ExtendDesc:Doll's eyes. They are the same color as Saku's eyes, but a\nclearer and deeper shade. They appear to have been carefully\nstored by someone, as there is not a speck of dust on them.>",
    "occasion": 3,
    "price": 0,
    "repeats": 1,
    "scope": 0,
    "speed": 0,
    "successRate": 100,
    "tpGain": 0
  },
  {
    "id": 58,
    "animationId": 0,
    "consumable": false,
    "damage": {
      "critical": false,
      "elementId": 0,
      "formula": "0",
      "type": 0,
      "variance": 20
    },
    "description": "",
    "effects": [],
    "hitType": 0,
    "iconIndex": 0,
    "itypeId": 1,
    "name": "Doll's Heart",
    "note": "HideItemNumber\n\n<ExtendDesc:The heart of a doll. A heart that beats warmly, brimming\nwith vitality. It is clear that this is the life of Sakuo,\nand it is the last part that must never be missing. Let's\nbreathe new life into Sakuo quickly.>",
    "occasion": 3,
    "price": 0,
    "repeats": 1,
    "scope": 0,
    "speed": 0,
    "successRate": 100,
    "tpGain": 0
  },
  {
    "id": 59,
    "animationId": 0,
    "consumable": false,
    "damage": {
      "critical": false,
      "elementId": 0,
      "formula": "0",
      "type": 0,
      "variance": 20
    },
    "description": "",
    "effects": [],
    "hitType": 0,
    "iconIndex": 0,
    "itypeId": 1,
    "name": "Small Cross",
    "note": "HideItemNumber\n\n<ExtendDesc:A small cross found in a western-style mansion. Made of a\nlight material, perhaps for a child. Did the child who owned\nthis have blessings that matched their faith?>",
    "occasion": 3,
    "price": 0,
    "repeats": 1,
    "scope": 0,
    "speed": 0,
    "successRate": 100,
    "tpGain": 0
  },
  {
    "id": 60,
    "animationId": 0,
    "consumable": false,
    "damage": {
      "critical": false,
      "elementId": 0,
      "formula": "0",
      "type": 0,
      "variance": 20
    },
    "description": "A sickle made for harvesting rice. The still sharp blade is\nuseful for obtaining a bountiful harvest.",
    "effects": [],
    "hitType": 0,
    "iconIndex": 0,
    "itypeId": 1,
    "name": "Rice Harvesting Sickle",
    "note": "HideItemNumber",
    "occasion": 3,
    "price": 0,
    "repeats": 1,
    "scope": 0,
    "speed": 0,
    "successRate": 100,
    "tpGain": 0
  },
  {
    "id": 61,
    "animationId": 0,
    "consumable": false,
    "damage": {
      "critical": false,
      "elementId": 0,
      "formula": "0",
      "type": 0,
      "variance": 20
    },
    "description": "The harvest of rice grown by infusing the power of divine\nenergy into withered rice plants. With proper processing, it\nwould likely become brown rice suitable for consumption.",
    "effects": [],
    "hitType": 0,
    "iconIndex": 0,
    "itypeId": 1,
    "name": "Rich Rice Ears",
    "note": "HideItemNumber",
    "occasion": 3,
    "price": 0,
    "repeats": 1,
    "scope": 0,
    "speed": 0,
    "successRate": 100,
    "tpGain": 0
  },
  {
    "id": 62,
    "animationId": 0,
    "consumable": false,
    "damage": {
      "critical": false,
      "elementId": 0,
      "formula": "0",
      "type": 0,
      "variance": 20
    },
    "description": "Leaves of mugwort that were growing wild outside a private\nhouse. They are fresh and green, but inedible as they are.",
    "effects": [],
    "hitType": 0,
    "iconIndex": 0,
    "itypeId": 1,
    "name": "Mugwort Leaf",
    "note": "HideItemNumber",
    "occasion": 3,
    "price": 0,
    "repeats": 1,
    "scope": 0,
    "speed": 0,
    "successRate": 100,
    "tpGain": 0
  },
  {
    "id": 63,
    "animationId": 0,
    "consumable": false,
    "damage": {
      "critical": false,
      "elementId": 0,
      "formula": "0",
      "type": 0,
      "variance": 20
    },
    "description": "Shiitake mushrooms that were growing from a decayed tree.\nThey have grown splendidly, but they seem inedible without\ncooking.",
    "effects": [],
    "hitType": 0,
    "iconIndex": 0,
    "itypeId": 1,
    "name": "Shiitake Mushroom",
    "note": "HideItemNumber",
    "occasion": 3,
    "price": 0,
    "repeats": 1,
    "scope": 0,
    "speed": 0,
    "successRate": 100,
    "tpGain": 0
  },
  {
    "id": 64,
    "animationId": 0,
    "consumable": false,
    "damage": {
      "critical": false,
      "elementId": 0,
      "formula": "0",
      "type": 0,
      "variance": 20
    },
    "description": "A brown rice porridge filled with mugwort and shiitake\nmushrooms. The steamy bowl emits an appetizing aroma of new\nrice.",
    "effects": [],
    "hitType": 0,
    "iconIndex": 0,
    "itypeId": 1,
    "name": "Freshly Made Rice Porridge",
    "note": "HideItemNumber",
    "occasion": 3,
    "price": 0,
    "repeats": 1,
    "scope": 0,
    "speed": 0,
    "successRate": 100,
    "tpGain": 0
  },
  {
    "id": 65,
    "animationId": 0,
    "consumable": false,
    "damage": {
      "critical": false,
      "elementId": 0,
      "formula": "0",
      "type": 0,
      "variance": 20
    },
    "description": "A rice ball wrapped in beautiful bamboo leaves. Luxuriously\nmade with white rice, it feels imbued with certain faith and\nprayer.",
    "effects": [],
    "hitType": 0,
    "iconIndex": 0,
    "itypeId": 1,
    "name": "Rice ball wrapped in bamboo leaves",
    "note": "HideItemNumber",
    "occasion": 3,
    "price": 0,
    "repeats": 1,
    "scope": 0,
    "speed": 0,
    "successRate": 100,
    "tpGain": 0
  },
  {
    "id": 66,
    "animationId": 0,
    "consumable": false,
    "damage": {
      "critical": false,
      "elementId": 0,
      "formula": "0",
      "type": 0,
      "variance": 20
    },
    "description": "",
    "effects": [],
    "hitType": 0,
    "iconIndex": 0,
    "itypeId": 1,
    "name": "Prayer Tachi (or Prayer Long Sword)",
    "note": "HideItemNumber\n\n<ExtendDesc:A sword found in the mansion. It appears to be very old, but\nit is imbued with a deep power of prayer. With this blade,\nit is likely possible to exorcise even a powerful curse.>",
    "occasion": 3,
    "price": 0,
    "repeats": 1,
    "scope": 0,
    "speed": 0,
    "successRate": 100,
    "tpGain": 0
  },
  {
    "id": 67,
    "animationId": 0,
    "consumable": false,
    "damage": {
      "critical": false,
      "elementId": 0,
      "formula": "0",
      "type": 0,
      "variance": 20
    },
    "description": "",
    "effects": [],
    "hitType": 0,
    "iconIndex": 0,
    "itypeId": 1,
    "name": "Vermilion Comb",
    "note": "HideItemNumber\n\n<ExtendDesc:The comb found in Saku's room. The red comb with moon\ndecorations is a relic of Saku, who was sacrificed, and it\nharbors the last remaining thoughts of Saku.>",
    "occasion": 3,
    "price": 0,
    "repeats": 1,
    "scope": 0,
    "speed": 0,
    "successRate": 100,
    "tpGain": 0
  },
  {
    "id": 68,
    "animationId": 0,
    "consumable": false,
    "damage": {
      "critical": false,
      "elementId": 0,
      "formula": "0",
      "type": 0,
      "variance": 20
    },
    "description": "A heavy brass key with a solid build. It's terribly cold but\nseems sturdy enough to open a strong door.",
    "effects": [],
    "hitType": 0,
    "iconIndex": 0,
    "itypeId": 1,
    "name": "Brass Key",
    "note": "HideItemNumber",
    "occasion": 3,
    "price": 0,
    "repeats": 1,
    "scope": 0,
    "speed": 0,
    "successRate": 100,
    "tpGain": 0
  },
  {
    "id": 69,
    "animationId": 0,
    "consumable": false,
    "damage": {
      "critical": false,
      "elementId": 0,
      "formula": "0",
      "type": 0,
      "variance": 20
    },
    "description": "",
    "effects": [],
    "hitType": 0,
    "iconIndex": 0,
    "itypeId": 1,
    "name": "Stainless Key",
    "note": "HideItemNumber\n\n<ExtendDesc:A stainless key that shines silver. It's still new, but\nthere's a slight residue of a curse left on it. The owner of\nthis must have been defeated by the curse.>",
    "occasion": 3,
    "price": 0,
    "repeats": 1,
    "scope": 0,
    "speed": 0,
    "successRate": 100,
    "tpGain": 0
  },
  {
    "id": 70,
    "animationId": 0,
    "consumable": false,
    "damage": {
      "critical": false,
      "elementId": 0,
      "formula": "0",
      "type": 0,
      "variance": 20
    },
    "description": "A well-made key. It has black and white decorative cords\nattached, which somehow remind one of a whaling curtain.",
    "effects": [],
    "hitType": 0,
    "iconIndex": 0,
    "itypeId": 1,
    "name": "Key with a Decorative Cord",
    "note": "HideItemNumber",
    "occasion": 3,
    "price": 0,
    "repeats": 1,
    "scope": 0,
    "speed": 0,
    "successRate": 100,
    "tpGain": 0
  },
  {
    "id": 71,
    "animationId": 0,
    "consumable": false,
    "damage": {
      "critical": false,
      "elementId": 0,
      "formula": "0",
      "type": 0,
      "variance": 20
    },
    "description": "A large key made of iron. It is heavy, but despite its old\nappearance, it is not rusty at all. What was this key\nprotecting?",
    "effects": [],
    "hitType": 0,
    "iconIndex": 0,
    "itypeId": 1,
    "name": "Iron Key",
    "note": "HideItemNumber",
    "occasion": 3,
    "price": 0,
    "repeats": 1,
    "scope": 0,
    "speed": 0,
    "successRate": 100,
    "tpGain": 0
  },
  {
    "id": 72,
    "animationId": 0,
    "consumable": false,
    "damage": {
      "critical": false,
      "elementId": 0,
      "formula": "0",
      "type": 0,
      "variance": 20
    },
    "description": "A key made of silver. It is decorated with extremely fine\ndetails, and a crescent moon pattern is engraved on it.",
    "effects": [],
    "hitType": 0,
    "iconIndex": 0,
    "itypeId": 1,
    "name": "Silverwork Key",
    "note": "HideItemNumber",
    "occasion": 3,
    "price": 0,
    "repeats": 1,
    "scope": 0,
    "speed": 0,
    "successRate": 100,
    "tpGain": 0
  },
  {
    "id": 73,
    "animationId": 0,
    "consumable": true,
    "damage": {
      "critical": false,
      "elementId": 0,
      "formula": "0",
      "type": 0,
      "variance": 20
    },
    "description": "",
    "effects": [],
    "hitType": 0,
    "iconIndex": 0,
    "itypeId": 1,
    "name": "",
    "note": "",
    "occasion": 0,
    "price": 0,
    "repeats": 1,
    "scope": 7,
    "speed": 0,
    "successRate": 100,
    "tpGain": 0
  },
  {
    "id": 74,
    "animationId": 0,
    "consumable": true,
    "damage": {
      "critical": false,
      "elementId": 0,
      "formula": "0",
      "type": 0,
      "variance": 20
    },
    "description": "",
    "effects": [],
    "hitType": 0,
    "iconIndex": 0,
    "itypeId": 1,
    "name": "",
    "note": "",
    "occasion": 0,
    "price": 0,
    "repeats": 1,
    "scope": 7,
    "speed": 0,
    "successRate": 100,
    "tpGain": 0
  },
  {
    "id": 75,
    "animationId": 0,
    "consumable": true,
    "damage": {
      "critical": false,
      "elementId": 0,
      "formula": "0",
      "type": 0,
      "variance": 20
    },
    "description": "",
    "effects": [],
    "hitType": 0,
    "iconIndex": 0,
    "itypeId": 1,
    "name": "",
    "note": "",
    "occasion": 0,
    "price": 0,
    "repeats": 1,
    "scope": 7,
    "speed": 0,
    "successRate": 100,
    "tpGain": 0
  },
  {
    "id": 76,
    "animationId": 0,
    "consumable": true,
    "damage": {
      "critical": false,
      "elementId": 0,
      "formula": "0",
      "type": 0,
      "variance": 20
    },
    "description": "",
    "effects": [],
    "hitType": 0,
    "iconIndex": 0,
    "itypeId": 1,
    "name": "",
    "note": "",
    "occasion": 0,
    "price": 0,
    "repeats": 1,
    "scope": 7,
    "speed": 0,
    "successRate": 100,
    "tpGain": 0
  },
  {
    "id": 77,
    "animationId": 0,
    "consumable": true,
    "damage": {
      "critical": false,
      "elementId": 0,
      "formula": "0",
      "type": 0,
      "variance": 20
    },
    "description": "",
    "effects": [],
    "hitType": 0,
    "iconIndex": 0,
    "itypeId": 1,
    "name": "",
    "note": "",
    "occasion": 0,
    "price": 0,
    "repeats": 1,
    "scope": 7,
    "speed": 0,
    "successRate": 100,
    "tpGain": 0
  },
  {
    "id": 78,
    "animationId": 0,
    "consumable": true,
    "damage": {
      "critical": false,
      "elementId": 0,
      "formula": "0",
      "type": 0,
      "variance": 20
    },
    "description": "",
    "effects": [],
    "hitType": 0,
    "iconIndex": 0,
    "itypeId": 1,
    "name": "",
    "note": "",
    "occasion": 0,
    "price": 0,
    "repeats": 1,
    "scope": 7,
    "speed": 0,
    "successRate": 100,
    "tpGain": 0
  },
  {
    "id": 79,
    "animationId": 0,
    "consumable": true,
    "damage": {
      "critical": false,
      "elementId": 0,
      "formula": "0",
      "type": 0,
      "variance": 20
    },
    "description": "",
    "effects": [],
    "hitType": 0,
    "iconIndex": 0,
    "itypeId": 1,
    "name": "",
    "note": "",
    "occasion": 0,
    "price": 0,
    "repeats": 1,
    "scope": 7,
    "speed": 0,
    "successRate": 100,
    "tpGain": 0
  },
  {
    "id": 80,
    "animationId": 0,
    "consumable": true,
    "damage": {
      "critical": false,
      "elementId": 0,
      "formula": "0",
      "type": 0,
      "variance": 20
    },
    "description": "",
    "effects": [],
    "hitType": 0,
    "iconIndex": 0,
    "itypeId": 1,
    "name": "",
    "note": "",
    "occasion": 0,
    "price": 0,
    "repeats": 1,
    "scope": 7,
    "speed": 0,
    "successRate": 100,
    "tpGain": 0
  }
]
